proxyzoo/__init__.py
proxyzoo/daemon.py
proxyzoo/launcher.py
proxyzoo/utils.py
proxyzoo/conf/__init__.py
proxyzoo/conf/config.py
proxyzoo/haproxy/__init__.py
proxyzoo/haproxy/executor.py
proxyzoo/haproxy/template.py
proxyzoo/httpserver/__init__.py
proxyzoo/httpserver/response.py
proxyzoo/httpserver/server.py
proxyzoo/zk/__init__.py
proxyzoo/zk/sync.py
proxyzoo-1.0.3.dist-info/METADATA
proxyzoo-1.0.3.dist-info/WHEEL
proxyzoo-1.0.3.dist-info/top_level.txt
proxyzoo-1.0.3.dist-info/RECORD
